oneNeuron/__init__.py
oneNeuron/all_utils.py
oneNeuron/perceptron.py
OneNeuron_pypi_Vani_Bhatia-0.0.3.dist-info/LICENSE
OneNeuron_pypi_Vani_Bhatia-0.0.3.dist-info/METADATA
OneNeuron_pypi_Vani_Bhatia-0.0.3.dist-info/WHEEL
OneNeuron_pypi_Vani_Bhatia-0.0.3.dist-info/top_level.txt
OneNeuron_pypi_Vani_Bhatia-0.0.3.dist-info/RECORD
