Metadata-Version: 2.1
Name: OneNeuron-pypi-Vani-Bhatia
Version: 0.0.3
Summary: It's an implementation of perceptron class and function for preparing the data,saving the model,create and save the plot
Home-page: https://github.com/Vani Bhatia/OneNeuron_pypi
Author: USER_NAME
Author-email: vanibhatia13@gmail.com
License: UNKNOWN
Project-URL: Bug Tracker, https://github.com/Vani Bhatia/OneNeuron_pypi/issues
Platform: UNKNOWN
Classifier: Programming Language :: Python :: 3
Classifier: License :: OSI Approved :: MIT License
Classifier: Operating System :: OS Independent
Requires-Python: >=3.7
License-File: LICENSE
Requires-Dist: numpy
Requires-Dist: tqdm
Requires-Dist: matplotlib
Requires-Dist: pandas
Requires-Dist: joblib
